{
  "build": "py_0",
  "build_number": 0,
  "channel": "https://repo.anaconda.com/pkgs/main/noarch",
  "constrains": [],
  "depends": [
    "python"
  ],
  "extracted_package_dir": "/home/manuj/anaconda3/pkgs/contextlib2-0.6.0.post1-py_0",
  "features": "",
  "files": [
    "lib/python3.8/site-packages/contextlib2-0.6.0.post1.dist-info/INSTALLER",
    "lib/python3.8/site-packages/contextlib2-0.6.0.post1.dist-info/LICENSE.txt",
    "lib/python3.8/site-packages/contextlib2-0.6.0.post1.dist-info/METADATA",
    "lib/python3.8/site-packages/contextlib2-0.6.0.post1.dist-info/RECORD",
    "lib/python3.8/site-packages/contextlib2-0.6.0.post1.dist-info/WHEEL",
    "lib/python3.8/site-packages/contextlib2-0.6.0.post1.dist-info/top_level.txt",
    "lib/python3.8/site-packages/contextlib2.py",
    "lib/python3.8/site-packages/__pycache__/contextlib2.cpython-38.pyc"
  ],
  "fn": "contextlib2-0.6.0.post1-py_0.conda",
  "legacy_bz2_md5": "8e3a0e55e9a89fe0c21679999d4b74bd",
  "legacy_bz2_size": 16805,
  "license": "PSF 2",
  "license_family": "PSF",
  "link": {
    "source": "/home/manuj/anaconda3/pkgs/contextlib2-0.6.0.post1-py_0",
    "type": 1
  },
  "md5": "64a18e6bdc9c1f6d675a7fd1a709750e",
  "name": "contextlib2",
  "noarch": "python",
  "package_tarball_full_path": "/home/manuj/anaconda3/pkgs/contextlib2-0.6.0.post1-py_0.conda",
  "package_type": "noarch_python",
  "paths_data": {
    "paths": [
      {
        "_path": "lib/python3.8/site-packages/__pycache__/contextlib2.cpython-38.pyc",
        "path_type": "pyc_file"
      }
    ],
    "paths_version": 1
  },
  "requested_spec": "contextlib2==0.6.0.post1=py_0",
  "sha256": "b7a9ee148a4437da4c6210e200702037de476ca321b8846530053cd1e3e0a595",
  "size": 16520,
  "subdir": "noarch",
  "timestamp": 1573937996392,
  "track_features": "",
  "url": "https://repo.anaconda.com/pkgs/main/noarch/contextlib2-0.6.0.post1-py_0.conda",
  "version": "0.6.0.post1"
}